esb1c/__init__.py
esb1c_app-0.1.5.dist-info/licenses/LICENSE
esb1c_app-0.1.5.dist-info/METADATA
esb1c_app-0.1.5.dist-info/WHEEL
esb1c_app-0.1.5.dist-info/top_level.txt
esb1c_app-0.1.5.dist-info/RECORD
