Metadata-Version: 2.4
Name: esb1c-app
Version: 0.1.5
Summary: Builder AMQP connection to 1C:ESB application
Author-email: Vladimir Nadulich <g240596448@gmail.com>
License-Expression: MIT
Project-URL: Homepage, https://gitlab.com/240596448/esb1c_app
Project-URL: Documentation, https://gitlab.com/240596448/esb1c_app/-/blob/master/README.md
Project-URL: Repository, https://gitlab.com/240596448/esb1c_app.git
Project-URL: Bug Tracker, https://gitlab.com/240596448/esb1c_app/issues
Keywords: 1c,onec,esb,client,amqp
Requires-Python: >=3.9
License-File: LICENSE
Requires-Dist: requests>=2.31
Provides-Extra: dev
Requires-Dist: pytest>=8.0; extra == "dev"
Dynamic: license-file
